mytb/__init__.py
mytb/aio/__init__.py
mytb/aio/compat.py
mytb/argparse.py
mytb/cli.py
mytb/commands/__init__.py
mytb/csv.py
mytb/datetime.py
mytb/debug.py
mytb/exceptions.py
mytb/file/__init__.py
mytb/file/find.py
mytb/file/suffix_file.py
mytb/gitlab/__init__.py
mytb/gitlab/check_ci_cfg.py
mytb/html/__init__.py
mytb/html/table_reader.py
mytb/importlib/__init__.py
mytb/ipc/__init__.py
mytb/ipc/mutex.py
mytb/ipc/posix_mutex.py
mytb/ipc/win_mutex.py
mytb/ipython.py
mytb/logging/__init__.py
mytb/logging/config.py
mytb/logging/configs/__init__.py
mytb/logging/configs/console.py
mytb/logging/handlers/__init__.py
mytb/lru_cache.py
mytb/memory.py
mytb/minibelt.py
mytb/modules.py
mytb/objects.py
mytb/os.py
mytb/parse.py
mytb/path.py
mytb/pickle.py
mytb/pprint.py
mytb/string.py
mytb/tempfile.py
mytb/tests/__init__.py
mytb/tests/gitlab/__init__.py
mytb/tests/gitlab/cicfg_patterns.py
mytb/tests/test_aio.py
mytb/tests/test_argparse.py
mytb/tests/test_datetime.py
mytb/tests/test_gitlab.py
mytb/tests/test_ipc.py
mytb/tests/test_lru_cache.py
mytb/tests/test_path.py
mytb/tests/test_string.py
mytb-0.1.3.dist-info/entry_points.txt
mytb-0.1.3.dist-info/LICENSE.txt
mytb-0.1.3.dist-info/WHEEL
mytb-0.1.3.dist-info/METADATA
mytb-0.1.3.dist-info/RECORD
