Metadata-Version: 2.1
Name: mytb
Version: 0.1.3
Summary: my toolbox for everyday python projects
Home-page: https://github.com/feenes/mytb
License: MIT
Author: Teledomic
Author-email: info@teledomic.eu
Requires-Python: >=3.6,<4
Classifier: License :: OSI Approved :: MIT License
Classifier: Programming Language :: Python :: 3
Classifier: Programming Language :: Python :: 3.10
Classifier: Programming Language :: Python :: 3.6
Classifier: Programming Language :: Python :: 3.7
Classifier: Programming Language :: Python :: 3.8
Classifier: Programming Language :: Python :: 3.9
Provides-Extra: all
Provides-Extra: date
Provides-Extra: gitlab
Provides-Extra: minimal
Requires-Dist: dateutils; extra == "all" or extra == "date"
Requires-Dist: ddt; extra == "all" or extra == "gitlab"
Requires-Dist: pytz; extra == "all" or extra == "date"
Requires-Dist: pyyaml; extra == "all" or extra == "gitlab"
Requires-Dist: tzlocal; extra == "all" or extra == "date"
Requires-Dist: unidecode
Project-URL: Repository, https://github.com/feenes/mytb.git
